kork/__init__.py
kork/ast.py
kork/ast_printer.py
kork/chain.py
kork/display.py
kork/environment.py
kork/examples.py
kork/exceptions.py
kork/foreign_funcs.py
kork/interpreter.py
kork/parser.py
kork/prompt_adapter.py
kork/py.typed
kork/retrieval.py
kork/utils.py
kork/version.py
kork-0.0.3.dist-info/WHEEL
kork-0.0.3.dist-info/LICENSE
kork-0.0.3.dist-info/METADATA
kork-0.0.3.dist-info/RECORD
