Metadata-Version: 2.1
Name: kork
Version: 0.0.3
Summary: Natural Language Interfaces Powered by LLMs
Home-page: https://github.com/langchain-ai/kork
License: MIT
Author: LangChain
Requires-Python: >=3.8.1,<4.0.0
Classifier: License :: OSI Approved :: MIT License
Classifier: Programming Language :: Python :: 3
Classifier: Programming Language :: Python :: 3.9
Classifier: Programming Language :: Python :: 3.10
Classifier: Programming Language :: Python :: 3.11
Requires-Dist: langchain (>=0.0.110)
Requires-Dist: lark (>=1.1.5,<2.0.0)
Requires-Dist: openai (>=0.27,<0.28)
Requires-Dist: sphinx-design (>=0.4.1,<0.5.0)
Project-URL: Repository, https://github.com/langchain-ai/kork
